pyimg_process/Methods.py
pyimg_process/__init__.py
pyimg_process-1.3.5.dist-info/LICENSE
pyimg_process-1.3.5.dist-info/METADATA
pyimg_process-1.3.5.dist-info/WHEEL
pyimg_process-1.3.5.dist-info/top_level.txt
pyimg_process-1.3.5.dist-info/RECORD
