Metadata-Version: 2.1
Name: pyimg-process
Version: 1.3.5
Summary: A simple package for image processing
Home-page: https://github.com/jonamelibia/pyimg-process
Download-URL: https://github.com/jonamelibia/pyimg-process/archive/refs/tags/1.3.4.tar.gz
Author: Mikel Agirrebeitia & Jon Amelibia
Author-email: jon.amelibia@alumni.mondragon.edu
License: MIT
Keywords: Image proceessing,Easy to use,Simple
Classifier: Development Status :: 3 - Alpha
Classifier: Intended Audience :: Developers
Classifier: Topic :: Software Development :: Build Tools
Classifier: License :: OSI Approved :: MIT License
Classifier: Programming Language :: Python :: 3
Classifier: Programming Language :: Python :: 3.7
Classifier: Programming Language :: Python :: 3.8
Classifier: Programming Language :: Python :: 3.9
License-File: LICENSE
Requires-Dist: numpy
Requires-Dist: matplotlib
Requires-Dist: opencv-python
